[
  {
    "type": "goal-only",
    "title": "Jednoduchý",
    "description": "Jednoduchý svet s prázdnou futbalovou bránkou",
    "image": "goalOnly"
  },
  {
    "type": "goal-random-ball",
    "title": "Náhodná lopta",
    "description": "Lopta sa objaví na náhodnom mieste na ihrisku",
    "image": "random"
  },
  {
    "type": "goal-and-obstacles",
    "title": "Prekážky",
    "description": "Svet s prekážkami rozpoznateľnými na snímke z kamery",
    "image": "obstacles"
  },
  {
    "type": "soccer",
    "title": "Tím vs. tím",
    "description": "Každý robot hrá sám za seba, s vlastným trénovacím modelom",
    "image": "soccer"
  }
]